asyncapi_python_parser_jonaslagoni/__init__.py
asyncapi_python_parser_jonaslagoni/parser.py
asyncapi_python_parser_jonaslagoni/traits.py
asyncapi_python_parser_jonaslagoni/validator.py
asyncapi_python_parser_jonaslagoni/models/asyncapi_1_0_0/ApiKey.py
asyncapi_python_parser_jonaslagoni/models/asyncapi_1_0_0/ApiKeyHttpSecurityScheme.py
asyncapi_python_parser_jonaslagoni/models/asyncapi_1_0_0/ApiKeyHttpSecuritySchemeIn.py
asyncapi_python_parser_jonaslagoni/models/asyncapi_1_0_0/ApiKeyHttpSecuritySchemeType.py
asyncapi_python_parser_jonaslagoni/models/asyncapi_1_0_0/ApiKeyIn.py
asyncapi_python_parser_jonaslagoni/models/asyncapi_1_0_0/ApiKeyType.py
asyncapi_python_parser_jonaslagoni/models/asyncapi_1_0_0/AsymmetricEncryption.py
asyncapi_python_parser_jonaslagoni/models/asyncapi_1_0_0/AsymmetricEncryptionType.py
asyncapi_python_parser_jonaslagoni/models/asyncapi_1_0_0/AsyncApi1Dot0SchemaDot.py
asyncapi_python_parser_jonaslagoni/models/asyncapi_1_0_0/Asyncapi.py
asyncapi_python_parser_jonaslagoni/models/asyncapi_1_0_0/BearerHttpSecurityScheme.py
asyncapi_python_parser_jonaslagoni/models/asyncapi_1_0_0/BearerHttpSecuritySchemeScheme.py
asyncapi_python_parser_jonaslagoni/models/asyncapi_1_0_0/BearerHttpSecuritySchemeType.py
asyncapi_python_parser_jonaslagoni/models/asyncapi_1_0_0/Components.py
asyncapi_python_parser_jonaslagoni/models/asyncapi_1_0_0/Contact.py
asyncapi_python_parser_jonaslagoni/models/asyncapi_1_0_0/ExternalDocs.py
asyncapi_python_parser_jonaslagoni/models/asyncapi_1_0_0/Info.py
asyncapi_python_parser_jonaslagoni/models/asyncapi_1_0_0/JsonMinusSchemaMinusDraftMinus07MinusSchema.py
asyncapi_python_parser_jonaslagoni/models/asyncapi_1_0_0/JsonMinusSchemaMinusDraftMinus07MinusSchemaSimpleTypes.py
asyncapi_python_parser_jonaslagoni/models/asyncapi_1_0_0/License.py
asyncapi_python_parser_jonaslagoni/models/asyncapi_1_0_0/Message.py
asyncapi_python_parser_jonaslagoni/models/asyncapi_1_0_0/Reference.py
asyncapi_python_parser_jonaslagoni-0.5.0.dist-info/METADATA
asyncapi_python_parser_jonaslagoni-0.5.0.dist-info/WHEEL
asyncapi_python_parser_jonaslagoni-0.5.0.dist-info/RECORD
